soundstorm_pytorch/__init__.py
soundstorm_pytorch/attend.py
soundstorm_pytorch/soundstorm.py
soundstorm_pytorch/trainer.py
soundstorm_pytorch-0.6.1.dist-info/licenses/LICENSE
soundstorm_pytorch-0.6.1.dist-info/METADATA
soundstorm_pytorch-0.6.1.dist-info/WHEEL
soundstorm_pytorch-0.6.1.dist-info/top_level.txt
soundstorm_pytorch-0.6.1.dist-info/RECORD
