Metadata-Version: 2.4
Name: soundstorm-pytorch
Version: 0.6.1
Summary: SoundStorm - Efficient Parallel Audio Generation from Google Deepmind, in Pytorch
Home-page: https://github.com/lucidrains/soundstorm-pytorch
Author: Phil Wang
Author-email: lucidrains@gmail.com
License: MIT
Keywords: artificial intelligence,deep learning,transformers,attention mechanism,audio generation
Classifier: Development Status :: 4 - Beta
Classifier: Intended Audience :: Developers
Classifier: Topic :: Scientific/Engineering :: Artificial Intelligence
Classifier: License :: OSI Approved :: MIT License
Classifier: Programming Language :: Python :: 3.6
License-File: LICENSE
Requires-Dist: accelerate
Requires-Dist: audiolm-pytorch>=1.2.8
Requires-Dist: beartype
Requires-Dist: classifier-free-guidance-pytorch>=0.1.5
Requires-Dist: hyper-connections>=0.1.15
Requires-Dist: einops>=0.8.0
Requires-Dist: spear-tts-pytorch>=0.4.0
Requires-Dist: torch>=2.2
Dynamic: author
Dynamic: author-email
Dynamic: classifier
Dynamic: description-content-type
Dynamic: home-page
Dynamic: keywords
Dynamic: license
Dynamic: license-file
Dynamic: requires-dist
Dynamic: summary
